neural_snr/__init__.py
neural_snr/core.py
neural_snr/inference.py
neural_snr/DeepFilterNet3/config.ini
neural_snr/DeepFilterNet3/enhance.log
neural_snr/DeepFilterNet3/checkpoints/model_120.ckpt.best
mashood_neural_snr-0.1.4.dist-info/LICENSE
mashood_neural_snr-0.1.4.dist-info/METADATA
mashood_neural_snr-0.1.4.dist-info/WHEEL
mashood_neural_snr-0.1.4.dist-info/top_level.txt
mashood_neural_snr-0.1.4.dist-info/RECORD
