Metadata-Version: 2.1
Name: mashood-neural-snr
Version: 0.1.4
Summary: Blind SNR estimation using DeepFilterNet. Includes bundled model weights.
Home-page: https://github.com/mashoodAwan/mashood-neural-snr
Author: Muhammad Mashood Awan
Author-email: mashoodawan27@gmail.com
License: MIT
Platform: UNKNOWN
Classifier: Programming Language :: Python :: 3
Classifier: License :: OSI Approved :: MIT License
Classifier: Operating System :: OS Independent
Requires-Python: >=3.8
License-File: LICENSE
Requires-Dist: torch==2.0.1
Requires-Dist: torchaudio==2.0.2
Requires-Dist: numpy
Requires-Dist: scipy
Requires-Dist: pandas
Requires-Dist: deepfilternet
Requires-Dist: soundfile
Requires-Dist: tqdm
